{
	"DEF": {
		"Name":"Default",
	},
	"ANJ": {
		"Name" :"Anji Mito",
		"Short":"Anji"
	},
	"ANS": {
		"Name":"Answer"
	},
    "AXL": {
		"Name" :"Axl Low",
		"Short":"Axl"
	},
	"BED": {
		"Name":"Bedman"
	},
	"BEDQ": {
		"Name":"Bedman?"
	},
    "BGT": {
		"Name":"Bridget"
	},
    "BKN": {
		"Name":"Baiken"
	},
    "CHP": {
		"Name" :"Chipp Zanuff",
		"Short":"Chipp"
	},
    "COS": {
		"Name" :"Happy Chaos",
		"Short":"Chaos"
	},
	"DZY": {
		"Name":"Dizzy"
	},
	"ELP": {
		"Name" :"Elphelt Valentine",
		"Short":"Elphelt"
	},
    "FAU": {
		"Name":"Faust"
	},
    "GIO": {
		"Name":"Giovanna"
	},
    "GLD": {
		"Name" :"Goldlewis Dickinson",
		"Short":"Goldlewis"
	},
    "INO": {
		"Name":"I-No"
	},
	"JAM": {
		"Name" :"Jam Kuradoberi",
		"Short":"Jam"
	},
	"JHN": {
		"Name":"Johnny"
	},
    "JKO": {
		"Name" :"Jack-O' Valentine",
		"Short":"Jack-O"
	},
	"JKO_Adult": {
		"Name" :"Jack-O' Valentine (Adult)",
		"Short":"Jack-O (Adult)"
	},
	"JKO_Child": {
		"Name" :"Jack-O' Valentine (Child)",
		"Short":"Jack-O (Child)"
	},
    "KYK": {
		"Name" :"Ky Kiske",
		"Short":"Ky",
	},
	"KUM": {
		"Name" :"Kum Haehyun",
		"Short":"Haehyun"
	},
    "LEO": {
		"Name" :"Leo Whitefang",
		"Short":"Leo"
	},
    "MAY": {
		"Name":"May"
	},
    "MLL": {
		"Name" :"Millia Rage",
		"Short":"Millia"
	},
    "NAG": {
		"Name":"Nagoriyuki"
	},
    "POT": {
		"Name":"Potemkin"
	},
    "RAM": {
		"Name" :"Ramlethal Valentine",
		"Short":"Ram"
	},
	"RVN": {
		"Name":"Raven"
	},
    "SIN": {
		"Name" :"Sin Kiske",
		"Short":"Sin"
	},
	"SLY": {
		"Name":"Slayer"
	},
    "SOL": {
		"Name" :"Sol Badguy",
		"Short":"Sol"
	},
    "TST": {
		"Name":"Testament"
	},
	"VEN": {
		"Name":"Venom"
	},
    "ZAT": {
		"Name" :"Zato-ONE",
		"Short":"Zato"
	},
}